enlight/__init__.py
enlight/data/__init__.py
enlight/data/collector.py
enlight/data/iterable_dataset.py
enlight/data/replay.py
enlight/data/replay_aug.py
enlight/envs/__init__.py
enlight/envs/_dm_patch.py
enlight/envs/atari.py
enlight/envs/dm_control.py
enlight/envs/vec_env.py
enlight/envs/wrappers.py
enlight/model/__init__.py
enlight/model/backbone.py
enlight/model/dm_control.py
enlight/rl/__init__.py
enlight/rl/distributions.py
enlight/rl/algo/__init__.py
enlight/rl/algo/sac.py
enlight/utils/__init__.py
enlight/utils/logger.py
enlight/utils/torch_utils.py
enlight-0.0.2.dist-info/LICENSE
enlight-0.0.2.dist-info/METADATA
enlight-0.0.2.dist-info/WHEEL
enlight-0.0.2.dist-info/entry_points.txt
enlight-0.0.2.dist-info/top_level.txt
enlight-0.0.2.dist-info/RECORD
