Metadata-Version: 2.1
Name: enlight
Version: 0.0.2
Summary: Fast and lightweight vision-based RL framework
Home-page: UNKNOWN
Author: Enlight developers
License: mit
Keywords: Deep Learning,Reinforcement Learning,Computer Vision
Platform: UNKNOWN
Classifier: Development Status :: 3 - Alpha
Classifier: Topic :: Scientific/Engineering :: Artificial Intelligence
Classifier: Environment :: Console
Classifier: Programming Language :: Python :: 3
Requires-Python: >=3.7
